portfolio_optimize/__init__.py
portfolio_optimize/optimizer.py
portfolio_optimize-1.2.2.dist-info/LICENSE
portfolio_optimize-1.2.2.dist-info/METADATA
portfolio_optimize-1.2.2.dist-info/WHEEL
portfolio_optimize-1.2.2.dist-info/top_level.txt
portfolio_optimize-1.2.2.dist-info/RECORD
