Metadata-Version: 2.1
Name: portfolio-optimize
Version: 1.2.2
Summary: A Python package for portfolio optimization. (Note: This package is under ongoing development. Contributions and corrections are welcome!)
Home-page: https://github.com/manujajay/portfolio-optimize
Author: Manu Jayawardana
Author-email: manujajayawardanais@gmail.com
Classifier: Programming Language :: Python :: 3
Classifier: License :: OSI Approved :: MIT License
Classifier: Operating System :: OS Independent
Requires-Python: >=3.6
License-File: LICENSE
Requires-Dist: numpy
Requires-Dist: pandas
Requires-Dist: yfinance
Requires-Dist: matplotlib
Requires-Dist: tqdm
